bayesprev.py
bayesprev-0.1.1.dist-info/LICENSE
bayesprev-0.1.1.dist-info/WHEEL
bayesprev-0.1.1.dist-info/METADATA
bayesprev-0.1.1.dist-info/RECORD
